<?xml version="1.0" encoding="utf-8"?>
<otobo_config version="2.0" init="Config">
    <Setting Name="Frontend::Output::FilterElementPost###StdSubject" Required="0" Valid="1">
        <Description Translatable="1">Defines standard subjects for some actions.</Description>
        <Navigation>Frontend::Base::OutputFilter</Navigation>
        <Value>
            <Hash>
                <Item Key="Module">Kernel::Output::HTML::FilterElementPost::StdSubject</Item>
                <Item Key="Debug">0</Item>
                <Item Key="Templates">
                    <Hash>
                        <Item Key="AgentTicketNote">1</Item>
                        <Item Key="AgentTicketPhoneInbound">1</Item>
                        <Item Key="AgentTicketPhoneOutbound">1</Item>
                        <Item Key="AgentTicketPhoneCommon">1</Item>
                        <Item Key="AgentTicketClose">1</Item>
                        <Item Key="AgentTicketPending">1</Item>
                        <Item Key="AgentTicketEmailOutbound">1</Item>
                    </Hash>
                </Item>
            </Hash>
        </Value>
    </Setting>
    <Setting Name="StdSubject::Subjects" Required="0" Valid="1">
        <Description Translatable="1">Defines standard subjects for some actions.</Description>
        <Navigation>Frontend::Base::OutputFilter</Navigation>
        <Value>
            <Hash>
               <Item Key="AgentTicketNote"><![CDATA[<TicketNumber> <Title> - Test]]></Item>
               <Item Key="AgentTicketPhoneInbound"><![CDATA[<TicketNumber> <Title> - Test]]></Item>
               <Item Key="AgentTicketPhoneOutbound"><![CDATA[<TicketNumber> <Title> - Test]]></Item>
               <Item Key="*"><![CDATA[<TicketNumber> <Title> - Test]]></Item>
            </Hash>
        </Value>
    </Setting>
</otobo_config>
